pyhpp/__init__.py
pyhpp/a_star.py
pyhpp/dijkstra.py
pyhpp/grid.py
pyhpp/model.py
pyhpp/node.py
pyhpp/tools.py
tests/__init__.py
tests/test_a_star/__init__.py
tests/test_a_star/test_a_star.py
tests/test_grid/__init__.py
tests/test_grid/test_grid.py
tests/test_model/__init__.py
tests/test_model/test_model.py
tests/test_tools/__init__.py
tests/test_tools/test_tools.py
pyhpp-0.1.5.dist-info/METADATA
pyhpp-0.1.5.dist-info/WHEEL
pyhpp-0.1.5.dist-info/top_level.txt
pyhpp-0.1.5.dist-info/RECORD
