Metadata-Version: 2.1
Name: pyhpp
Version: 0.1.5
Summary: Algorithms for Three Dimensional Path Planning
Home-page: https://github.com/Kun-Neng/hpp/tree/main/python
Author: Kun-Neng Hung
Author-email: kunneng.hung@gmail.com
License: UNKNOWN
Platform: UNKNOWN
Classifier: Programming Language :: Python :: 3
Classifier: License :: OSI Approved :: MIT License
Classifier: Operating System :: OS Independent
Requires-Python: >=3.6
